{"date":"\"date\": \"YYYY-10-11\"","image":"https://raw.githubusercontent.com/peinarte/peinarteblog/main/image/articulos/chignon-elegante-tu-look-profesional-impecable.png","title":"Chignon Elegante: Tu Look Profesional Impecable","summary":"Transforma tu imagen con este chignon sofisticado, ideal para reuniones importantes o tu jornada laboral. Irradia confianza y distinción con un peinado que proyecta profesionalismo y buen gusto. ¡Eleva tu estilo ejecutivo al siguiente nivel!\n#PeinadoProfesional #ChignonElegante #EstiloDeOficina #LookEjecutivo #CabelloProfesional","category":"Peinados Elegantes y Profesionales","filename":"\"filename\":\"chignon-elegante-tu-look-profesional-impecable.html\""}